engineai/sdk/__init__.py
engineai/sdk/py.typed
engineai/sdk/api/__init__.py
engineai/sdk/api/app.py
engineai/sdk/api/app_authorization_rule.py
engineai/sdk/api/auth.py
engineai/sdk/api/client.py
engineai/sdk/api/dashboard.py
engineai/sdk/api/dashboard_version.py
engineai/sdk/api/graphql_client.py
engineai/sdk/api/group.py
engineai/sdk/api/group_member.py
engineai/sdk/api/workspace.py
engineai/sdk/api/workspace_member.py
engineai/sdk/cli/__init__.py
engineai/sdk/cli/cli.py
engineai/sdk/cli/commands/__init__.py
engineai/sdk/cli/commands/app.py
engineai/sdk/cli/commands/app_rule.py
engineai/sdk/cli/commands/auth.py
engineai/sdk/cli/commands/dashboard.py
engineai/sdk/cli/commands/group.py
engineai/sdk/cli/commands/group_member.py
engineai/sdk/cli/commands/workspace.py
engineai/sdk/cli/commands/workspace_member.py
engineai/sdk/cli/template/content/main.py
engineai/sdk/dashboard/__init__.py
engineai/sdk/dashboard/base.py
engineai/sdk/dashboard/exceptions.py
engineai/sdk/dashboard/interface.py
engineai/sdk/dashboard/selected.py
engineai/sdk/dashboard/templated_string.py
engineai/sdk/dashboard/utils.py
engineai/sdk/dashboard/abstract/__init__.py
engineai/sdk/dashboard/abstract/layout.py
engineai/sdk/dashboard/abstract/selectable_widgets.py
engineai/sdk/dashboard/abstract/typing.py
engineai/sdk/dashboard/dashboard/__init__.py
engineai/sdk/dashboard/dashboard/dashboard.py
engineai/sdk/dashboard/dashboard/page/__init__.py
engineai/sdk/dashboard/dashboard/page/dependency.py
engineai/sdk/dashboard/dashboard/page/page.py
engineai/sdk/dashboard/dashboard/page/root.py
engineai/sdk/dashboard/dashboard/page/route.py
engineai/sdk/dashboard/dashboard/version/__init__.py
engineai/sdk/dashboard/dashboard/version/version.py
engineai/sdk/dashboard/data/__init__.py
engineai/sdk/dashboard/data/exceptions.py
engineai/sdk/dashboard/data/connectors/__init__.py
engineai/sdk/dashboard/data/connectors/duck_db/__init__.py
engineai/sdk/dashboard/data/connectors/duck_db/duck_db.py
engineai_sdk-0.139.0.dist-info/licenses/LICENSE
engineai_sdk-0.139.0.dist-info/METADATA
engineai_sdk-0.139.0.dist-info/WHEEL
engineai_sdk-0.139.0.dist-info/entry_points.txt
engineai_sdk-0.139.0.dist-info/top_level.txt
engineai_sdk-0.139.0.dist-info/RECORD
