Metadata-Version: 2.4
Name: engineai.sdk
Version: 0.139.0
Summary: EngineAI's Platform SDK
Author-email: Pedro Rodrigues <pedro@dystematic.com>
Maintainer-email: Pedro Cunha <cunha@engineai.com>, Pedro Feiteira <feiteira@engineai.com>, Nuno Silva <nuno@engineai.com>
License-Expression: MIT
Project-URL: Documentation, https://docs.engineai.com/
Requires-Python: <3.14,>=3.10
License-File: LICENSE
Requires-Dist: numpy<3,>=1
Requires-Dist: pandas<3,>=1
Requires-Dist: click<9,>=8
Requires-Dist: typing-extensions<5,>=4
Requires-Dist: requests<3,>=2
Requires-Dist: orjson<4,>3.9.15
Requires-Dist: rich<15,>=12
Dynamic: license-file
